{
  "Micro-Mini" :  {
    "default": { "front": { "bottom": "b05_front_micro_mini_flared",  "belt": "belt_front", "neckline": "t01_front" }, "back": { "bottom": "b05_micro_mini_flared_back", "belt":"default_belt_back", "neckline": "default_t01_back" } },
    "t2": { "default": { "front": {  "neckline": "t02_front" }, "back": { "neckline": "t02_back" } } },
    "t3": { "default": {"front": {  "neckline": "t03_front" }, "back": { "neckline": "t03_back" } } },
    "t4": { "default": { "front": {  "neckline": "t04_front" }, "back": { "neckline": "t04_back" } } },
    "t22":{ "default":{ "front": { "behind": ["t22_front"] }, "back": { "infront": ["t22_back"] } } },
    "t27":{ "default":{ "front": { "behind": ["t27_base" ]}, "back": { "infront": ["t27_back_base"]} },
            "t2": { "front": { "behind": ["t27_curved" ]}, "back": { "infront": ["t27_back_curved"]} },
            "t3": { "front": { "behind": ["t27_sweatheart" ]}, "back": { "infront": ["t27_back_sweatheart"]} },
            "t4": { "front": { "behind": ["t27_straight"]}, "back": { "infront": ["t27_back_straight"]} }
          },
    "t29": { "default":{ "front": { "behind": ["t29_front_base"]}, "back": { "infront": ["t29_base_back"]} },
            "t2": { "front": { "behind": ["t29_front_curved"]}, "back": { "infront": ["t29_curved_back"]} },
            "t3": { "front": { "behind": ["t29_front_sweatheart"]}, "back": { "infront": ["t29_sweatheart_back"]} },
            "t4": { "front": { "behind": ["t29_front_straight"]}, "back": { "infront": ["t29_straight_back"]} }
           },
    "t31":{ "default":{ "front": { "behind": ["t31_front"] }, "back": { "infront": ["t31_back"] } } },
    "t33":{ "default":{ "front": { "behind": ["t33_front"] }, "back": { "infront": ["t33_back"] } } },
    "t34":{ "default":{ "front": { "behind": ["t34_front"] }, "back": { "infront": ["t34_back"] } } },
    "t35":{ "default":{ "front": { "behind": ["t35_front"] }, "back": { "infront": ["t35_back"] } } },    
    "t44":{ "default":{ "front": { "behind": ["t44_front"] }, "back": { "infront": ["t44_back"] } } },
    "t51":{ "default":{ "front": { "behind": ["t51_front"] }, "back": { "infront": ["t51_back"] } } },
    "t58":{ "default":{ "back": { "infront": ["t58_back"] } } },
    "b20":{ "default":{ "front": { "behind": ["b20_front"] }, "back": { "behind": ["b20_back"] } } },
    "a1":{ "default":{ "front": { "infront": ["a01_front"] }, "back": { "behind": ["a01_back"] } } },
    "a2":{ "default":{ "front": { "belt": ["a02_front"] }, "back": { "belt": ["a02_back"] } } },
    "a5":{ "default":{  "back": { "infront": ["a05_back_top"] } } },    
    "b3":{ "default":{ "front": { "bottom": ["b03_front_micro_mini_fitted"] }, "back": { "bottom": ["b03_micro_mini_fitted_back"] } } }

  },
  "Knee": {
    "default": { "front":{"bottom": "b05_front_knee", "belt": "belt_front","neckline": "t01_front" }, "back": {"bottom": "b05_knee_back", "belt":"default_belt_back"} },
    "t2": { "default": { "front": {  "neckline": "t02_front" }, "back": { "neckline": "t02_back" } } },
    "t3": { "default": {"front": {  "neckline": "t03_front" }, "back": { "neckline": "t03_back" } } },
    "t4": { "default": { "front": {  "neckline": "t04_front" }, "back": { "neckline": "t04_back" } } },
    "t22":{ "default":{ "front": { "behind": ["t22_front"] }, "back": { "infront": ["t22_back"] } } },
    "t27":{ "default":{ "front": { "behind": ["t27_base" ]}, "back": { "infront": ["t27_back_base"]} },
            "t2": { "front": { "behind": ["t27_curved" ]}, "back": { "infront": ["t27_back_curved"]} },
            "t3": { "front": { "behind": ["t27_sweatheart" ]}, "back": { "infront": ["t27_back_sweatheart"]} },
            "t4": { "front": { "behind": ["t27_straight"]}, "back": { "infront": ["t27_back_straight"]} }
          },
    "t29": { "default":{ "front": { "behind": ["t29_front_base"]}, "back": { "infront": ["t29_base_back"]} },
            "t2": { "front": { "behind": ["t29_front_curved"]}, "back": { "infront": ["t29_curved_back"]} },
            "t3": { "front": { "behind": ["t29_front_sweatheart"]}, "back": { "infront": ["t29_sweatheart_back"]} },
            "t4": { "front": { "behind": ["t29_front_straight"]}, "back": { "infront": ["t29_straight_back"]} }
           },
    "t31":{ "default":{ "front": { "behind": ["t31_front"] }, "back": { "infront": ["t31_back"] } } },
    "t33":{ "default":{ "front": { "behind": ["t33_front"] }, "back": { "infront": ["t33_back"] } } },
    "t34":{ "default":{ "front": { "behind": ["t34_front"] }, "back": { "infront": ["t34_back"] } } },
    "t35":{ "default":{ "front": { "behind": ["t35_front"] }, "back": { "infront": ["t35_back"] } } },    
    "t44":{ "default":{ "front": { "behind": ["t44_front"] }, "back": { "infront": ["t44_back"] } } },
    "t51":{ "default":{ "front": { "behind": ["t51_front"] }, "back": { "infront": ["t51_back"] } } },
    "t58":{ "default":{ "back": { "infront": ["t58_back"] } } },
    "b20":{ "default":{ "front": { "behind": ["b20_front"] }, "back": { "behind": ["b20_back"] } } },
    "a1":{ "default":{ "front": { "infront": ["a01_front"] }, "back": { "behind": ["a01_back"] } } },
    "a2":{ "default":{ "front": { "belt": ["a02_front"] }, "back": { "belt": ["a02_back"] } } },
    "a5":{ "default":{  "back": { "infront": ["a05_back_top"] } } },        
    "b1":{ "default":{ "front": { "bottom": ["b01_front_knee"] }, "back": { "bottom": ["b01_back_knee"] } } },
    "b3":{ "default":{ "front": { "bottom": ["b03_front_knee"] }, "back": { "bottom": ["b03_knee_back"] } } },
    "b13":{ "default":{ "front": { "bottom": ["b13_knee"] } } }
    
  },
  "Mini": {
    "default": { "front" : {"bottom": "b05_front_mini", "belt": "belt_front","neckline":"t01_front"  }, "back": { "bottom": "b05_mini_back", "belt":"default_belt_back"} },
    "t2": { "default": { "front": {  "neckline": "t02_front" }, "back": { "neckline": "t02_back" } } },
    "t3": { "default": {"front": {  "neckline": "t03_front" }, "back": { "neckline": "t03_back" } } },
    "t4": { "default": { "front": {  "neckline": "t04_front" }, "back": { "neckline": "t04_back" } } },
    "t22":{ "default":{ "front": { "behind": ["t22_front"] }, "back": { "infront": ["t22_back"] } } },
    "t27":{ "default":{ "front": { "behind": ["t27_base" ]}, "back": { "infront": ["t27_back_base"]} },
            "t2": { "front": { "behind": ["t27_curved" ]}, "back": { "infront": ["t27_back_curved"]} },
            "t3": { "front": { "behind": ["t27_sweatheart" ]}, "back": { "infront": ["t27_back_sweatheart"]} },
            "t4": { "front": { "behind": ["t27_straight"]}, "back": { "infront": ["t27_back_straight"]} }
          },
    "t29": { "default":{ "front": { "behind": ["t29_front_base"]}, "back": { "infront": ["t29_base_back"]} },
            "t2": { "front": { "behind": ["t29_front_curved"]}, "back": { "infront": ["t29_curved_back"]} },
            "t3": { "front": { "behind": ["t29_front_sweatheart"]}, "back": { "infront": ["t29_sweatheart_back"]} },
            "t4": { "front": { "behind": ["t29_front_straight"]}, "back": { "infront": ["t29_straight_back"]} }
           },
    "t31":{ "default":{ "front": { "behind": ["t31_front"] }, "back": { "infront": ["t31_back"] } } },
    "t33":{ "default":{ "front": { "behind": ["t33_front"] }, "back": { "infront": ["t33_back"] } } },
    "t34":{ "default":{ "front": { "behind": ["t34_front"] }, "back": { "infront": ["t34_back"] } } },
    "t35":{ "default":{ "front": { "behind": ["t35_front"] }, "back": { "infront": ["t35_back"] } } },    
    "t44":{ "default":{ "front": { "behind": ["t44_front"] }, "back": { "infront": ["t44_back"] } } },
    "t51":{ "default":{ "front": { "behind": ["t51_front"] }, "back": { "infront": ["t51_back"] } } },
    "t58":{ "default":{ "back": { "infront": ["t58_back"] } } },
    "b20":{ "default":{ "front": { "behind": ["b20_front"] }, "back": { "behind": ["b20_back"] } } },
    "a1":{ "default":{ "front": { "infront": ["a01_front"] }, "back": { "behind": ["a01_back"] } } },
    "a2":{ "default":{ "front": { "belt": ["a02_front"] }, "back": { "belt": ["a02_back"] } } },
    "a5":{ "default":{  "back": { "infront": ["a05_back_top"] } } },        
    "b1":{ "default":{ "front": { "bottom": ["b01_front_mini"] }, "back": { "bottom": ["b01_mini_back"] } } },
    "b3":{ "default":{ "front": { "bottom": ["b03_front_mini"] }, "back": { "bottom": ["b03_mini_back"] } } }
  },
  "Midi": {
    "default":{ "front":{ "bottom": "b05_midi_front","belt": "belt_front", "neckline": "t01_front"}, "back":{"bottom":"b05_midi_81_quad_001", "belt":"default_belt_back"} },
    "t2": { "default": { "front": {  "neckline": "t02_front" }, "back": { "neckline": "t02_back" } } },
    "t3": { "default": {"front": {  "neckline": "t03_front" }, "back": { "neckline": "t03_back" } } },
    "t4": { "default": { "front": {  "neckline": "t04_front" }, "back": { "neckline": "t04_back" } } },
    "t22":{ "default":{ "front": { "behind": ["t22_front"] }, "back": { "infront": ["t22_back"] } } },
    "t27":{ "default":{ "front": { "behind": ["t27_base" ]}, "back": { "infront": ["t27_back_base"]} },
            "t2": { "front": { "behind": ["t27_curved" ]}, "back": { "infront": ["t27_back_curved"]} },
            "t3": { "front": { "behind": ["t27_sweatheart" ]}, "back": { "infront": ["t27_back_sweatheart"]} },
            "t4": { "front": { "behind": ["t27_straight"]}, "back": { "infront": ["t27_back_straight"]} }
          },
    "t29": { "default":{ "front": { "behind": ["t29_front_base"]}, "back": { "infront": ["t29_base_back"]} },
            "t2": { "front": { "behind": ["t29_front_curved"]}, "back": { "infront": ["t29_curved_back"]} },
            "t3": { "front": { "behind": ["t29_front_sweatheart"]}, "back": { "infront": ["t29_sweatheart_back"]} },
            "t4": { "front": { "behind": ["t29_front_straight"]}, "back": { "infront": ["t29_straight_back"]} }
           },
    "t31":{ "default":{ "front": { "behind": ["t31_front"] }, "back": { "infront": ["t31_back"] } } },
    "t33":{ "default":{ "front": { "behind": ["t33_front"] }, "back": { "infront": ["t33_back"] } } },
    "t34":{ "default":{ "front": { "behind": ["t34_front"] }, "back": { "infront": ["t34_back"] } } },
    "t35":{ "default":{ "front": { "behind": ["t35_front"] }, "back": { "infront": ["t35_back"] } } },    
    "t44":{ "default":{ "front": { "behind": ["t44_front"] }, "back": { "infront": ["t44_back"] } } },
    "t51":{ "default":{ "front": { "behind": ["t51_front"] }, "back": { "infront": ["t51_back"] } } },
    "t58":{ "default":{ "back": { "infront": ["t58_back"] } } },
    "b20":{ "default":{ "front": { "behind": ["b20_front"] }, "back": { "behind": ["b20_back"] } } },
    "a1":{ "default":{ "front": { "infront": ["a01_front"] }, "back": { "behind": ["a01_back"] } } },
    "a2":{ "default":{ "front": { "belt": ["a02_front"] }, "back": { "belt": ["a02_back"] } } },
    "a5":{ "default":{  "back": { "infront": ["a05_back_top"] } } },        
    "b1":{ "default":{ "front": { "bottom": ["b01_front_midi"] }, "back": { "bottom": ["b01_midi_back"] } } },
    "b3":{ "default":{ "front": { "bottom": ["b03_front_midi"] }, "back": { "bottom": ["b03_midi_back"] } } },
    "b13":{ "default":{ "front": { "bottom": ["b13_midi"] } } }
    
  },
  "Ankle": {
    "default": { "front": { "bottom": "b05_front_ankle", "belt": "belt_front", "neckline": "t01_front" },"back":{"bottom": "default_b05_ankle_back", "belt":"default_belt_back"} },
    "t2": { "default": { "front": {  "neckline": "t02_front" }, "back": { "neckline": "t02_back" } } },
    "t3": { "default": {"front": {  "neckline": "t03_front" }, "back": { "neckline": "t03_back" } } },
    "t4": { "default": { "front": {  "neckline": "t04_front" }, "back": { "neckline": "t04_back" } } },
    "t22":{ "default":{ "front": { "behind": ["t22_front"] }, "back": { "infront": ["t22_back"] } } },
    "t27":{ "default":{ "front": { "behind": ["t27_base" ]}, "back": { "infront": ["t27_back_base"]} },
            "t2": { "front": { "behind": ["t27_curved" ]}, "back": { "infront": ["t27_back_curved"]} },
            "t3": { "front": { "behind": ["t27_sweatheart" ]}, "back": { "infront": ["t27_back_sweatheart"]} },
            "t4": { "front": { "behind": ["t27_straight"]}, "back": { "infront": ["t27_back_straight"]} }
          },
    "t29": { "default":{ "front": { "behind": ["t29_front_base"]}, "back": { "infront": ["t29_base_back"]} },
            "t2": { "front": { "behind": ["t29_front_curved"]}, "back": { "infront": ["t29_curved_back"]} },
            "t3": { "front": { "behind": ["t29_front_sweatheart"]}, "back": { "infront": ["t29_sweatheart_back"]} },
            "t4": { "front": { "behind": ["t29_front_straight"]}, "back": { "infront": ["t29_straight_back"]} }
           },
    "t31":{ "default":{ "front": { "behind": ["t31_front"] }, "back": { "infront": ["t31_back"] } } },
    "t33":{ "default":{ "front": { "behind": ["t33_front"] }, "back": { "infront": ["t33_back"] } } },
    "t34":{ "default":{ "front": { "behind": ["t34_front"] }, "back": { "infront": ["t34_back"] } } },
    "t35":{ "default":{ "front": { "behind": ["t35_front"] }, "back": { "infront": ["t35_back"] } } },    
    "t44":{ "default":{ "front": { "behind": ["t44_front"] }, "back": { "infront": ["t44_back"] } } },
    "t51":{ "default":{ "front": { "behind": ["t51_front"] }, "back": { "infront": ["t51_back"] } } },
    "t58":{ "default":{ "back": { "infront": ["t58_back"] } } },
    "b20":{ "default":{ "front": { "behind": ["b20_front"] }, "back": { "behind": ["b20_back"] } } },
    "a1":{ "default":{ "front": { "infront": ["a01_front"] }, "back": { "behind": ["a01_back"] } } },
    "a2":{ "default":{ "front": { "belt": ["a02_front"] }, "back": { "belt": ["a02_back"] } } },
    "a5":{ "default":{  "back": { "infront": ["a05_back_top"] } } },        
    "b1":{ "default":{ "front": { "bottom": ["b01_front_ankle"] }, "back": { "bottom": ["b01_back_ankle"] } } },
    "b3":{ "default":{ "front": { "bottom": ["b03_front_ankle"] }, "back": { "bottom": ["b03_ankle_back"] } } },
    "b13":{ "default":{ "front": { "bottom": ["b13_ankle"] } } }
  },
  "Maxi": {
    "default": {"front": {"bottom" : "b05_front_maxi", "belt": "belt_front", "neckline": "t01_front"}, "back": { "bottom": "b05_maxi_back", "belt":"default_belt_back"} },
    "t2": { "default": { "front": {  "neckline": "t02_front" }, "back": { "neckline": "t02_back" } } },
    "t3": { "default": {"front": {  "neckline": "t03_front" }, "back": { "neckline": "t03_back" } } },
    "t4": { "default": { "front": {  "neckline": "t04_front" }, "back": { "neckline": "t04_back" } } },
    "t22":{ "default":{ "front": { "behind": ["t22_front"] }, "back": { "infront": ["t22_back"] } } },
    "t27":{ "default":{ "front": { "behind": ["t27_base" ]}, "back": { "infront": ["t27_back_base"]} },
            "t2": { "front": { "behind": ["t27_curved" ]}, "back": { "infront": ["t27_back_curved"]} },
            "t3": { "front": { "behind": ["t27_sweatheart" ]}, "back": { "infront": ["t27_back_sweatheart"]} },
            "t4": { "front": { "behind": ["t27_straight"]}, "back": { "infront": ["t27_back_straight"]} }
          },
    "t29": { "default":{ "front": { "behind": ["t29_front_base"]}, "back": { "infront": ["t29_base_back"]} },
            "t2": { "front": { "behind": ["t29_front_curved"]}, "back": { "infront": ["t29_curved_back"]} },
            "t3": { "front": { "behind": ["t29_front_sweatheart"]}, "back": { "infront": ["t29_sweatheart_back"]} },
            "t4": { "front": { "behind": ["t29_front_straight"]}, "back": { "infront": ["t29_straight_back"]} }
           },
    "t31":{ "default":{ "front": { "behind": ["t31_front"] }, "back": { "infront": ["t31_back"] } } },
    "t33":{ "default":{ "front": { "behind": ["t33_front"] }, "back": { "infront": ["t33_back"] } } },
    "t34":{ "default":{ "front": { "behind": ["t34_front"] }, "back": { "infront": ["t34_back"] } } },
    "t35":{ "default":{ "front": { "behind": ["t35_front"] }, "back": { "infront": ["t35_back"] } } },    
    "t44":{ "default":{ "front": { "behind": ["t44_front"] }, "back": { "infront": ["t44_back"] } } },
    "t51":{ "default":{ "front": { "behind": ["t51_front"] }, "back": { "infront": ["t51_back"] } } },
    "t58":{ "default":{ "back": { "infront": ["t58_back"] } } },
    "b20":{ "default":{ "front": { "behind": ["b20_front"] }, "back": { "behind": ["b20_back"] } } },
    "a1":{ "default":{ "front": { "infront": ["a01_front"] }, "back": { "behind": ["a01_back"] } } },
    "a2":{ "default":{ "front": { "belt": ["a02_front"] }, "back": { "belt": ["a02_back"] } } },
    "a5":{ "default":{  "back": { "infront": ["a05_back_top"] } } },        
    "b1":{ "default":{ "front": { "bottom": ["b01_front_maxi"] }, "back": { "bottom": ["b01_back_maxi"] } } },
    "b3":{ "default":{ "front": { "bottom": ["b03_front_maxi"] }, "back": { "bottom": ["b03_maxi_back"] } } },
    "b13":{ "default":{ "front": { "bottom": ["b13_maxi"] } } }
    
  }
}
